YOLOv7_with_depthmap/YOLOv7_with_depthmap.py
YOLOv7_with_depthmap/__init__.py
YOLOv7_with_depthmap/hubconf.py
YOLOv7_with_depthmap/models/common.py
YOLOv7_with_depthmap/models/experimental.py
YOLOv7_with_depthmap/models/yolo.py
YOLOv7_with_depthmap/utils/autoanchor.py
YOLOv7_with_depthmap/utils/datasets.py
YOLOv7_with_depthmap/utils/general.py
YOLOv7_with_depthmap/utils/google_utils.py
YOLOv7_with_depthmap/utils/loss.py
YOLOv7_with_depthmap/utils/metrics.py
YOLOv7_with_depthmap/utils/plots.py
YOLOv7_with_depthmap/utils/torch_utils.py
YOLOv7_with_depthmap-1.0.1.dist-info/LICENSE.md
YOLOv7_with_depthmap-1.0.1.dist-info/LICENSE.txt
YOLOv7_with_depthmap-1.0.1.dist-info/METADATA
YOLOv7_with_depthmap-1.0.1.dist-info/WHEEL
YOLOv7_with_depthmap-1.0.1.dist-info/top_level.txt
YOLOv7_with_depthmap-1.0.1.dist-info/RECORD
